dogehouse/__init__.py
dogehouse/constants.py
dogehouse/entities.py
dogehouse/events.py
dogehouse/parsers.py
dogehouse/py.typed
dogehouse/util.py
dogehouse-3.0.1.dist-info/LICENSE
dogehouse-3.0.1.dist-info/METADATA
dogehouse-3.0.1.dist-info/WHEEL
dogehouse-3.0.1.dist-info/top_level.txt
dogehouse-3.0.1.dist-info/RECORD
