Metadata-Version: 2.1
Name: dogehouse
Version: 3.0.1
Summary: Python wrapper for the dogehouse API
Home-page: https://github.com/tusharsadhwani/dogehouse.py
Author: Tushar Sadhwani
Author-email: tushar.sadhwani000@gmail.com
License: MIT
Platform: UNKNOWN
Classifier: License :: OSI Approved :: MIT License
Classifier: Operating System :: OS Independent
Classifier: Programming Language :: Python :: 3
Classifier: Programming Language :: Python :: 3 :: Only
Classifier: Programming Language :: Python :: 3.7
Classifier: Programming Language :: Python :: 3.8
Classifier: Programming Language :: Python :: 3.9
Requires-Python: >=3.6
Requires-Dist: websockets (==8.1)
Provides-Extra: dev
Requires-Dist: pytest (>=6.2.2) ; extra == 'dev'
